sushida/__init__.py
sushida/_constants.py
sushida/_image_processing.py
sushida/cli.py
sushida/game.py
sushida/webdriver.py
sushida-0.2.0.dist-info/entry_points.txt
sushida-0.2.0.dist-info/LICENSE
sushida-0.2.0.dist-info/WHEEL
sushida-0.2.0.dist-info/METADATA
sushida-0.2.0.dist-info/RECORD
